moonmining/__init__.py
moonmining/admin.py
moonmining/app_settings.py
moonmining/apps.py
moonmining/auth_hooks.py
moonmining/constants.py
moonmining/core.py
moonmining/forms.py
moonmining/helpers.py
moonmining/managers.py
moonmining/providers.py
moonmining/tasks.py
moonmining/urls.py
moonmining/locale/django.pot
moonmining/locale/de/LC_MESSAGES/django.po
moonmining/locale/en/LC_MESSAGES/django.po
moonmining/locale/es/LC_MESSAGES/django.po
moonmining/locale/fr_FR/LC_MESSAGES/django.po
moonmining/locale/it_IT/LC_MESSAGES/django.po
moonmining/locale/ja/LC_MESSAGES/django.po
moonmining/locale/ko_KR/LC_MESSAGES/django.po
moonmining/locale/ru/LC_MESSAGES/django.po
moonmining/locale/uk/LC_MESSAGES/django.po
moonmining/locale/zh_Hans/LC_MESSAGES/django.po
moonmining/management/commands/__init__.py
moonmining/management/commands/moonmining_calculate_all.py
moonmining/management/commands/moonmining_import_moons.py
moonmining/management/commands/moonmining_load_eve.py
moonmining/management/commands/moonstuff_export_moons.py
moonmining/migrations/0001_initial.py
moonmining/migrations/0002_add_mining_ledger.py
moonmining/migrations/0003_mining_ledger_reports.py
moonmining/migrations/0004_add_permission_moon_ledgers.py
moonmining/migrations/0005_make_pricing_more_flexible.py
moonmining/migrations/0006_add_labels.py
moonmining/migrations/0007_add_localization.py
moonmining/migrations/__init__.py
moonmining/models/__init__.py
moonmining/models/extractions.py
moonmining/models/general.py
moonmining/models/moons.py
moonmining/models/notifications.py
moonmining/models/owners.py
moonmining/static/moonmining/css/extractions.css
moonmining/static/moonmining/css/global.css
moonmining/static/moonmining/css/moonmining.css
moonmining/static/moonmining/css/moons.css
moonmining/static/moonmining/css/reports.css
moonmining/static/moonmining/img/Spinner-1s-64px-dark.gif
moonmining/static/moonmining/img/Spinner-1s-64px-light.gif
aa_moonmining-2.3.0.dist-info/licenses/LICENSE
aa_moonmining-2.3.0.dist-info/WHEEL
aa_moonmining-2.3.0.dist-info/METADATA
aa_moonmining-2.3.0.dist-info/RECORD
