Metadata-Version: 2.4
Name: aa-moonmining
Version: 2.3.0
Summary: Alliance Auth app for tracking moon extractions and scouting new moons.
Author-email: Erik Kalkoken <kaloken87@gmail.com>
Requires-Python: >=3.8
Classifier: Environment :: Web Environment
Classifier: Framework :: Django
Classifier: Framework :: Django :: 4.2
Classifier: Intended Audience :: End Users/Desktop
Classifier: License :: OSI Approved :: MIT License
Classifier: Operating System :: OS Independent
Classifier: Programming Language :: Python
Classifier: Programming Language :: Python :: 3.8
Classifier: Programming Language :: Python :: 3.9
Classifier: Programming Language :: Python :: 3.10
Classifier: Programming Language :: Python :: 3.11
Classifier: Programming Language :: Python :: 3.12
Classifier: Topic :: Internet :: WWW/HTTP
Classifier: Topic :: Internet :: WWW/HTTP :: Dynamic Content
License-File: LICENSE
Requires-Dist: allianceauth-app-utils>=1.28
Requires-Dist: allianceauth>=4,<5
Requires-Dist: django-bootstrap-form
Requires-Dist: django-datatables-view>=1.20
Requires-Dist: django-eveuniverse>=1.6
Requires-Dist: django-navhelper
Requires-Dist: PyYAML
Project-URL: Changelog, https://gitlab.com/ErikKalkoken/aa-moonmining/-/blob/master/CHANGELOG.md
Project-URL: Homepage, https://gitlab.com/ErikKalkoken/aa-moonmining
Project-URL: Source, https://gitlab.com/ErikKalkoken/aa-moonmining
Project-URL: Tracker, https://gitlab.com/ErikKalkoken/aa-moonmining/-/issues
